Topsis_Nipun_Garg_102003674/__init__.py
Topsis_Nipun_Garg_102003674/main.py
Topsis_Nipun_Garg_102003674-0.0.2.dist-info/LICENSE
Topsis_Nipun_Garg_102003674-0.0.2.dist-info/METADATA
Topsis_Nipun_Garg_102003674-0.0.2.dist-info/WHEEL
Topsis_Nipun_Garg_102003674-0.0.2.dist-info/top_level.txt
Topsis_Nipun_Garg_102003674-0.0.2.dist-info/RECORD
