Metadata-Version: 2.1
Name: Topsis_Nipun_Garg_102003674
Version: 0.0.2
Summary: A small example package
Author: Nipun Garg
Author-email: ngarg4_be20@thapar.edu
Classifier: Programming Language :: Python :: 3
Classifier: License :: OSI Approved :: MIT License
Classifier: Operating System :: OS Independent
Requires-Python: >=3.6
License-File: LICENSE
